LICENSE
MANIFEST.in
README.md
requirements.txt
setup.cfg
setup.py
gcp_airflow_foundations/__init__.py
gcp_airflow_foundations/parse_dags.py
gcp_airflow_foundations/version.py
gcp_airflow_foundations/base_class/__init__.py
gcp_airflow_foundations/base_class/data_source_table_config.py
gcp_airflow_foundations/base_class/dataflow_job_config.py
gcp_airflow_foundations/base_class/facebook_config.py
gcp_airflow_foundations/base_class/facebook_table_config.py
gcp_airflow_foundations/base_class/gcs_source_config.py
gcp_airflow_foundations/base_class/gcs_table_config.py
gcp_airflow_foundations/base_class/hds_metadata_config.py
gcp_airflow_foundations/base_class/hds_table_config.py
gcp_airflow_foundations/base_class/landing_zone_config.py
gcp_airflow_foundations/base_class/ods_metadata_config.py
gcp_airflow_foundations/base_class/ods_table_config.py
gcp_airflow_foundations/base_class/salesforce_ingestion_config.py
gcp_airflow_foundations/base_class/schema_options_config.py
gcp_airflow_foundations/base_class/source_config.py
gcp_airflow_foundations/base_class/source_table_config.py
gcp_airflow_foundations/base_class/utils.py
gcp_airflow_foundations/common/__init__.py
gcp_airflow_foundations/common/dataflow/__init__.py
gcp_airflow_foundations/common/dataflow/jdbc/__init__.py
gcp_airflow_foundations/common/dataflow/jdbc/dataflow_taskgroups.py
gcp_airflow_foundations/common/dataflow/jdbc/oracle/__init__.py
gcp_airflow_foundations/common/dataflow/jdbc/oracle/oracle_query_helpers.py
gcp_airflow_foundations/common/gcp/__init__.py
gcp_airflow_foundations/common/gcp/load_builder.py
gcp_airflow_foundations/common/gcp/hds/__init__.py
gcp_airflow_foundations/common/gcp/hds/schema_utils.py
gcp_airflow_foundations/common/gcp/ods/__init__.py
gcp_airflow_foundations/common/gcp/ods/schema_utils.py
gcp_airflow_foundations/common/gcp/source_schema/__init__.py
gcp_airflow_foundations/common/gcp/source_schema/bq.py
gcp_airflow_foundations/common/gcp/source_schema/gcs.py
gcp_airflow_foundations_dev_jiny.egg-info/PKG-INFO
gcp_airflow_foundations_dev_jiny.egg-info/SOURCES.txt
gcp_airflow_foundations_dev_jiny.egg-info/dependency_links.txt
gcp_airflow_foundations_dev_jiny.egg-info/requires.txt
gcp_airflow_foundations_dev_jiny.egg-info/top_level.txt